app/__init__.py
app/datanchor.py
app/wifi.ps1
datanchor-1.0.dist-info/METADATA
datanchor-1.0.dist-info/WHEEL
datanchor-1.0.dist-info/top_level.txt
datanchor-1.0.dist-info/RECORD
