Metadata-Version: 2.1
Name: datanchor
Version: 1.0
Summary: DAtAnchor Inc Python library
Home-page: https://github.com/dataanchor/dat-sdk
Author: Harihara Varma Indukuri
Author-email: hari@datanchor.io
License: MIT
Platform: UNKNOWN
Requires: requests
Requires: psutil
